ewoksdata/__init__.py
ewoksdata/data/__init__.py
ewoksdata/data/bliss.py
ewoksdata/data/contextiterator.py
ewoksdata/data/nexus.py
ewoksdata/data/url.py
ewoksdata/data/utils.py
ewoksdata/data/blissdata/__init__.py
ewoksdata/data/blissdata/blissdatav0.py
ewoksdata/data/blissdata/blissdatav1.py
ewoksdata/data/blissdata/blissdatav2.py
ewoksdata/data/hdf5/__init__.py
ewoksdata/data/hdf5/config.py
ewoksdata/data/hdf5/types.py
ewoksdata/data/hdf5/dataset_writer/__init__.py
ewoksdata/data/hdf5/dataset_writer/_base.py
ewoksdata/data/hdf5/dataset_writer/_non_sequential.py
ewoksdata/data/hdf5/dataset_writer/_non_sequential_stack.py
ewoksdata/data/hdf5/dataset_writer/_sequential.py
ewoksdata/data/hdf5/dataset_writer/_sequential_stack.py
ewoksdata/tests/__init__.py
ewoksdata/tests/conftest.py
ewoksdata/tests/test_contextiterator.py
ewoksdata/tests/test_data_bliss.py
ewoksdata/tests/test_data_hdf5.py
ewoksdata/tests/test_data_nexus.py
ewoksdata/tests/test_dataset_writer.py
ewoksdata/tests/data/__init__.py
ewoksdata/tests/data/bliss_scans.py
ewoksdata-2.1.0.dist-info/licenses/LICENSE.md
ewoksdata-2.1.0.dist-info/METADATA
ewoksdata-2.1.0.dist-info/WHEEL
ewoksdata-2.1.0.dist-info/top_level.txt
ewoksdata-2.1.0.dist-info/RECORD
