Metadata-Version: 2.4
Name: ewoksdata
Version: 2.1.0
Summary: Ewoks tasks for data access
Author-email: ESRF <dau-pydev@esrf.fr>
License: # MIT License
Project-URL: Homepage, https://gitlab.esrf.fr/workflow/ewoksapps/ewoksdata/
Project-URL: Documentation, https://ewoksdata.readthedocs.io
Project-URL: Repository, https://gitlab.esrf.fr/workflow/ewoksapps/ewoksdata/
Project-URL: Issues, https://gitlab.esrf.fr/workflow/ewoksapps/ewoksdata/issues
Project-URL: Changelog, https://gitlab.esrf.fr/workflow/ewoksapps/ewoksdata/-/blob/main/CHANGELOG.md
Classifier: Intended Audience :: Science/Research
Classifier: License :: OSI Approved :: MIT License
Classifier: Programming Language :: Python :: 3
Requires-Python: >=3.8
License-File: LICENSE.md
Requires-Dist: packaging
Requires-Dist: h5py>=2.8
Requires-Dist: silx>=1.1.0
Requires-Dist: hdf5plugin
Requires-Dist: blissdata>=0.3.4
Requires-Dist: redis
Requires-Dist: redis!=5.3.0b1,!=5.3.0b3
Requires-Dist: redis-om!=1.0.0b0; python_version < "3.9"
Requires-Dist: redis-om!=1.0.3b0; python_version < "3.9"
Provides-Extra: online
Requires-Dist: blissdata[tango]; extra == "online"
Provides-Extra: test
Requires-Dist: ewoksdata[online]; extra == "test"
Requires-Dist: pytest>=7; extra == "test"
Provides-Extra: dev
Requires-Dist: ewoksdata[test]; extra == "dev"
Requires-Dist: black>=25; extra == "dev"
Requires-Dist: flake8>=4; extra == "dev"
Requires-Dist: isort; extra == "dev"
Provides-Extra: doc
Requires-Dist: ewoksdata[test]; extra == "doc"
Requires-Dist: sphinx>=4.5; extra == "doc"
Requires-Dist: sphinx-autodoc-typehints>=1.16; extra == "doc"
Requires-Dist: pydata-sphinx-theme<0.15; extra == "doc"
Dynamic: license-file
